[
  {
    "itemphotos": [
      "fi1-1.png",
      "fi1-2.png"
    ],
    "name": "DIO フィギュア",
    "price": 14000,
    "state": "在庫なし",
    "text": "ジョジョの奇妙な冒険",
    "url": "product/1"
  },
  {
    "itemphotos": [
      "fi2-1.png",
      "fi2-2.png"
    ],
    "name": "キング 両翼決戦 フィギュア",
    "price": 10000,
    "state": "在庫あり",
    "text": "ワンピース",
    "url": "/product/2"
  },
  {
    "itemphotos": [
      "fi3-1.png",
      "fi3-2.png"
    ],
    "name": "ヤマト フィギュア",
    "price": 7000,
    "state": "在庫あり",
    "text": "ワンピース",
    "url": "/product/3"
  },
  {
    "itemphotos": [
      "fi4-1.png",
      "fi4-2.png"
    ],
    "name": "ギニュー フィギュア",
    "price": 10000,
    "state": "在庫あり",
    "text": "ドラゴンボール",
    "url": "/product/4"
  },
  {
    "itemphotos": [
      "fi5-1.png",
      "fi5-2.png"
    ],
    "name": "耳郎響香 フィギュア",
    "price": 9000,
    "state": "在庫なし",
    "text": "僕のヒーローアカデミア",
    "url": "/product/5"
  },
  {
    "itemphotos": [
      "fi6-1.png",
      "fi6-2.png"
    ],
    "name": "うちはサスケ フィギュア",
    "price": 2000,
    "state": "在庫あり",
    "text": "NARUTO",
    "url": "/product/6"
  },
  {
    "itemphotos": [
      "fi7-1.png",
      "fi7-2.png"
    ],
    "name": "デイダラ フィギュア",
    "price": 2000,
    "state": "在庫なし",
    "text": "NARUTO",
    "url": "/product/7"
  },
  {
    "itemphotos": [
      "fi8-1.png",
      "fi8-2.png"
    ],
    "name": "ルミナス フィギュア",
    "price": 2000,
    "state": "在庫あり",
    "text": "転生したらスライムだった件",
    "url": "/product/8"
  },
  {
    "itemphotos": [
      "fi9-1.png",
      "fi9-2.png"
    ],
    "name": "孫悟飯（ビースト） フィギュア",
    "price": 3000,
    "state": "在庫あり",
    "text": "ドラゴンボール",
    "url": "/product/9"
  },
  {
    "itemphotos": [
      "fi10-1.png",
      "fi10-2.png"
    ],
    "name": "河東ぱい フィギュア",
    "price": 4000,
    "state": "在庫あり",
    "text": "ぽんのみち",
    "url": "/product/10"
  },
  {
    "itemphotos": [
      "fi11-1.png",
      "fi11-2.png"
    ],
    "name": "大神ミオ フィギュア",
    "price": 4000,
    "state": "在庫なし",
    "text": "hololive",
    "url": "/product/11"
  }
]